mkdocstrings_handlers/python_betterrefs/__init__.py
mkdocstrings_handlers/python_betterrefs/config.py
mkdocstrings_handlers/python_betterrefs/crossref.py
mkdocstrings_handlers/python_betterrefs/handler.py
mkdocstrings_handlers/python_betterrefs/py.typed
mkdocstrings_python_betterrefs-1.0.2.dist-info/METADATA
mkdocstrings_python_betterrefs-1.0.2.dist-info/WHEEL
mkdocstrings_python_betterrefs-1.0.2.dist-info/licenses/LICENSE.txt
mkdocstrings_python_betterrefs-1.0.2.dist-info/licenses/NOTICE.md
mkdocstrings_python_betterrefs-1.0.2.dist-info/RECORD
