Metadata-Version: 2.4
Name: mkdocstrings-python-betterrefs
Version: 1.0.2
Summary: Extended mkdocstrings-python handler with better cross-references support
Project-URL: Homepage, https://itsdrike.github.com/mkdocstrings-python-betterrefs/
Project-URL: Documentation, https://itsdrike.github.com/mkdocstrings-python-betterrefs/
Project-URL: Repository, https://github.com/ItsDrike/mkdocstrings-python-betterrefs
Project-URL: Issues, https://github.com/ItsDrike/mkdocstrings-python-betterrefs/issues
Author-email: Christopher Barber <Christopher.Barber@analog.com>, ItsDrike <itsdrike@protonmail.com>
Maintainer-email: ItsDrike <itsdrike@protonmail.com>
License-Expression: Apache-2.0
License-File: LICENSE.txt
License-File: NOTICE.md
Keywords: documentation,mkdocstrings,mkdocstrings-handler
Classifier: Development Status :: 5 - Production/Stable
Classifier: Intended Audience :: Developers
Classifier: License :: OSI Approved :: Apache Software License
Classifier: Natural Language :: English
Classifier: Operating System :: OS Independent
Classifier: Programming Language :: Python
Classifier: Programming Language :: Python :: 3
Classifier: Programming Language :: Python :: 3 :: Only
Classifier: Programming Language :: Python :: 3.9
Classifier: Programming Language :: Python :: 3.10
Classifier: Programming Language :: Python :: 3.11
Classifier: Programming Language :: Python :: 3.12
Classifier: Programming Language :: Python :: 3.13
Classifier: Programming Language :: Python :: 3.14
Classifier: Topic :: Documentation
Classifier: Topic :: Software Development
Classifier: Topic :: Software Development :: Documentation
Classifier: Topic :: Utilities
Classifier: Typing :: Typed
Requires-Python: >=3.9
Requires-Dist: griffe>=1.0.0
Requires-Dist: mkdocstrings-python<1.15.0,>=1.14.1
Requires-Dist: typing-extensions>=4.0
